reqpy_M/__init__.py
reqpy_m-0.3.0.dist-info/licenses/LICENSE
reqpy_m-0.3.0.dist-info/METADATA
reqpy_m-0.3.0.dist-info/WHEEL
reqpy_m-0.3.0.dist-info/top_level.txt
reqpy_m-0.3.0.dist-info/RECORD
