Metadata-Version: 2.4
Name: reqpy-M
Version: 0.3.0
Summary: A Python module for spectral matching of earthquake records (Single, RotDnn, PSD/FAS)
Home-page: https://github.com/LuisMontejo/REQPY
Author: Luis A. Montejo
Author-email: luis.montejo@upr.edu
Project-URL: Bug Tracker, https://github.com/LuisMontejo/REQPY/issues
Classifier: Programming Language :: Python :: 3
Classifier: License :: OSI Approved :: MIT License
Classifier: Operating System :: OS Independent
Classifier: Topic :: Scientific/Engineering :: Physics
Classifier: Topic :: Scientific/Engineering :: Visualization
Classifier: Intended Audience :: Science/Research
Requires-Python: >=3.8
License-File: LICENSE
Requires-Dist: numpy
Requires-Dist: scipy>=1.6.0
Requires-Dist: matplotlib
Requires-Dist: numba
Provides-Extra: smoothing
Requires-Dist: pykooh; extra == "smoothing"
Dynamic: author
Dynamic: author-email
Dynamic: classifier
Dynamic: description
Dynamic: description-content-type
Dynamic: home-page
Dynamic: license-file
Dynamic: project-url
Dynamic: provides-extra
Dynamic: requires-dist
Dynamic: requires-python
Dynamic: summary
